fxgui/__init__.py
fxgui/examples.py
fxgui/fxconstants.py
fxgui/fxdcc.py
fxgui/fxicons.py
fxgui/fxstyle.py
fxgui/fxutils.py
fxgui/fxwidgets.py
fxgui/style.jsonc
fxgui/icons/favicon_dark.png
fxgui/icons/favicon_light.png
fxgui/icons/dcc/3d_equalizer.svg
fxgui/icons/dcc/adobe_photoshop.svg
fxgui/icons/dcc/adobe_substance_painter.svg
fxgui/icons/dcc/blender.svg
fxgui/icons/dcc/flow_production_tracking.svg
fxgui/icons/dcc/hiero.svg
fxgui/icons/dcc/houdini.svg
fxgui/icons/dcc/katana.svg
fxgui/icons/dcc/mari.svg
fxgui/icons/dcc/maya.svg
fxgui/icons/dcc/nuke.svg
fxgui/icons/dcc/open_exr.svg
fxgui/icons/dcc/open_rv.svg
fxgui/icons/dcc/redshift.svg
fxgui/icons/dcc/renderman.svg
fxgui/icons/dcc/rez.svg
fxgui/icons/dcc/usd.svg
fxgui/icons/dcc/zbrush.svg
fxgui/icons/stylesheet/Hmovetoolbar.png
fxgui/icons/stylesheet/Hsepartoolbar.png
fxgui/icons/stylesheet/Vmovetoolbar.png
fxgui/icons/stylesheet/Vsepartoolbar.png
fxgui/icons/stylesheet/branch_closed-on.png
fxgui/icons/stylesheet/branch_closed.png
fxgui/icons/stylesheet/branch_open-on.png
fxgui/icons/stylesheet/branch_open.png
fxgui/icons/stylesheet/checkbox_checked.png
fxgui/icons/stylesheet/checkbox_checked_disabled.png
fxgui/icons/stylesheet/checkbox_checked_focus.png
fxgui/icons/stylesheet/checkbox_indeterminate.png
fxgui/icons/stylesheet/checkbox_indeterminate_disabled.png
fxgui/icons/stylesheet/checkbox_indeterminate_focus.png
fxgui/icons/stylesheet/checkbox_unchecked.png
fxgui/icons/stylesheet/checkbox_unchecked_disabled.png
fxgui/icons/stylesheet/checkbox_unchecked_focus.png
fxgui/icons/stylesheet/close-hover.png
fxgui/icons/stylesheet/close-pressed.png
fxgui/icons/stylesheet/close.png
fxgui/icons/stylesheet/down_arrow.png
fxgui/icons/stylesheet/down_arrow_disabled.png
fxgui/icons/stylesheet/left_arrow.png
fxgui/icons/stylesheet/left_arrow_disabled.png
fxgui/icons/stylesheet/radio_checked.png
fxgui/icons/stylesheet/radio_checked_disabled.png
fxgui/icons/stylesheet/radio_checked_focus.png
fxgui-4.6.0.dist-info/LICENSE
fxgui-4.6.0.dist-info/METADATA
fxgui-4.6.0.dist-info/WHEEL
fxgui-4.6.0.dist-info/top_level.txt
fxgui-4.6.0.dist-info/RECORD
