Metadata-Version: 2.1
Name: fxgui
Version: 4.6.0
Summary: Custom Python classes and utilities tailored for Qt built UI, in VFX-oriented DCC applications.
Home-page: https://github.com/healkeiser/fxgui
Author: Valentin Beaumont
Author-email: valentin.onze@gmail.com
License: MIT
Project-URL: Documentation, https://healkeiser.github.io/fxgui
Project-URL: GitHub, https://github.com/healkeiser/fxgui
Project-URL: Changelog, https://github.com/healkeiser/fxgui/blob/main/CHANGELOG.md
Project-URL: Source, https://github.com/healkeiser/fxgui
Project-URL: Funding, https://github.com/sponsors/healkeiser
Keywords: Qt PySide2 VFX DCC UI
License-File: LICENSE
Requires-Dist: qtpy
Requires-Dist: QtAwesome
